Adafruit_ADXL345-1.0.1.dist-info/metadata.json
Adafruit_ADXL345-1.0.1.dist-info/METADATA
Adafruit_ADXL345-1.0.1.dist-info/RECORD
Adafruit_ADXL345-1.0.1.dist-info/WHEEL
Adafruit_ADXL345-1.0.1.dist-info/DESCRIPTION.rst
Adafruit_ADXL345-1.0.1.dist-info/dependency_links.txt
Adafruit_ADXL345-1.0.1.dist-info/top_level.txt
Adafruit_ADXL345/__init__.py
Adafruit_ADXL345/ADXL345.py
